[
    {
        "content": "<p>It sounds like you're talking about the <a href=\"https://en.wikipedia.org/wiki/Metropolis%E2%80%93Hastings_algorithm\">Metropolis algorithm</a>.</p>",
        "id": 261388344,
        "sender_full_name": "John Baez",
        "timestamp": 1636849369
    },
    {
        "content": "<p>Is that what you're talking about?</p>",
        "id": 261388354,
        "sender_full_name": "John Baez",
        "timestamp": 1636849388
    },
    {
        "content": "<p>Yes, exactly</p>",
        "id": 261417123,
        "sender_full_name": "Owen Lynch",
        "timestamp": 1636896455
    }
]