[
    {
        "content": "<p>Are there any results on decomposing a Lie groupoid(appropriately) into sub Lie groupoids?  Like in the case of manifolds we have the notion of foliation.</p>",
        "id": 271637941,
        "sender_full_name": "ADITTYA CHAUDHURI",
        "timestamp": 1644614150
    },
    {
        "content": "<p>I feel I should, but I don't know any results like that!</p>",
        "id": 271656585,
        "sender_full_name": "John Baez",
        "timestamp": 1644625233
    }
]